<?xml version="1.0" encoding="UTF-8" standalone="no"?>
<!DOCTYPE xml>
<question category="Playing" creationDate="2022-07-03T17:08:17.044790Z" horizontalTag="play these chords" id="cb15f725">
    <prompt>
        <standardOut text="Play these chords">
            <lilyPond clef="treble" image="true" lights="true" notes="true" template="singlestave.ly">
                <insert content="&lt;c e g&gt; &lt;b d g&gt; &lt;c e g&gt;2"/>
            </lilyPond>
        </standardOut>
    </prompt>
    <response expectedMidiScript="&lt;c e g&gt; &lt;b d g&gt; &lt;c e g&gt;" explainerClef="treble" explainerKeySignature="c \major" format="record-midi-sequence-then-submit"/>
    <hint>
        <standardOut text="C major, G major, C major"/>
    </hint>
</question>