<?xml version="1.0" encoding="UTF-8" standalone="no"?>
<!DOCTYPE xml>
<question category="Aural" creationDate="2022-08-01T16:25:38.677118Z" horizontalTag="match tune" id="5793d274" verticalTag="minor third">
    <prompt>
        <standardOut text="Match this tune">
            <lilyPond clef="treble" notes="true" template="singlestave.ly">
                <insert content="d f d2"/>
            </lilyPond>
        </standardOut>
    </prompt>
    <response format="radio-then-submit">
        <button correct="true" id="d85ef243">
            <standardOut>
                <lilyPond clef="treble" id="2dfd4212" notes="true" template="singlestave.ly">
                    <insert content="d f d2"/>
                </lilyPond>
            </standardOut>
        </button>
        <button id="645406f1">
            <standardOut>
                <lilyPond clef="treble" id="74b7103c" notes="true" template="singlestave.ly">
                    <insert content="ees a ees2"/>
                </lilyPond>
            </standardOut>
        </button>
        <button id="5c54974a">
            <standardOut>
                <lilyPond clef="treble" id="35af7f9e" notes="true" template="singlestave.ly">
                    <insert content="g' g b,2"/>
                </lilyPond>
            </standardOut>
        </button>
        <button id="1c33e2e1">
            <standardOut>
                <lilyPond clef="treble" id="f9f625fb" notes="true" template="singlestave.ly">
                    <insert content="c c cis2"/>
                </lilyPond>
            </standardOut>
        </button>
    </response>
    <hint/>
</question>